flask_discoverer.py
flask_discoverer-0.1.6.dist-info/LICENSE.md
flask_discoverer-0.1.6.dist-info/METADATA
flask_discoverer-0.1.6.dist-info/WHEEL
flask_discoverer-0.1.6.dist-info/top_level.txt
flask_discoverer-0.1.6.dist-info/RECORD
