Metadata-Version: 2.1
Name: flask-discoverer
Version: 0.1.6
Summary: Flask API autodiscovery
Home-page: http://github.com/adsabs/flask-discoverer/
Author: Vladimir Sudilovsky
Author-email: vsudilovsky@cfa.harvard.edu
License: MIT
Platform: any
Classifier: Environment :: Web Environment
Classifier: Intended Audience :: Developers
Classifier: License :: OSI Approved :: MIT License
Classifier: Operating System :: OS Independent
Classifier: Programming Language :: Python
Classifier: Topic :: Internet :: WWW/HTTP :: Dynamic Content
Classifier: Topic :: Software Development :: Libraries :: Python Modules
Classifier: Programming Language :: Python :: 2.7
Classifier: Programming Language :: Python :: 3.6
License-File: LICENSE.md
Requires-Dist: Flask ==0.12.4 ; python_version < "3.0"
Requires-Dist: Flask ==2.3.2 ; python_version > "3.0"
